prochoppy/__init__.py
prochoppy/__main__.py
prochoppy/cliutil.py
ProChopPy-0.1.2.dist-info/LICENSE
ProChopPy-0.1.2.dist-info/METADATA
ProChopPy-0.1.2.dist-info/WHEEL
ProChopPy-0.1.2.dist-info/entry_points.txt
ProChopPy-0.1.2.dist-info/top_level.txt
ProChopPy-0.1.2.dist-info/RECORD
