Metadata-Version: 2.1
Name: ProChopPy
Version: 0.1.2
Summary: Segment audio recordings into separate files based on ProRec annotations.
Home-page: https://github.com/thatfloflo/prochoppy
Author: Florian Breit
Author-email: florian@florian.me.uk
Project-URL: Bug Tracker, https://github.com/thatfloflo/prochoppy/issues
Classifier: Development Status :: 4 - Beta
Classifier: Environment :: Console
Classifier: Programming Language :: Python :: 3
Classifier: Programming Language :: Python :: 3.10
Classifier: License :: OSI Approved :: MIT License
Classifier: Operating System :: OS Independent
Classifier: Topic :: Multimedia :: Sound/Audio :: Conversion
Classifier: Topic :: Multimedia :: Sound/Audio :: Speech
Classifier: Topic :: Scientific/Engineering
Classifier: Topic :: Utilities
Requires-Python: >=3.10
License-File: LICENSE
Requires-Dist: colorama
